yt_updater/__init__.py
yt_updater/get_playlist.py
yt_updater/update_videos.py
yt_updater/youtube.py
yt_updater-0.2.3.dist-info/LICENSE
yt_updater-0.2.3.dist-info/METADATA
yt_updater-0.2.3.dist-info/WHEEL
yt_updater-0.2.3.dist-info/entry_points.txt
yt_updater-0.2.3.dist-info/RECORD
