Metadata-Version: 2.3
Name: yt-updater
Version: 0.2.3
Summary: 
Author: fluffy
Author-email: fluffy@beesbuzz.biz
Requires-Python: >=3.12,<3.14
Classifier: Programming Language :: Python :: 3
Classifier: Programming Language :: Python :: 3.12
Classifier: Programming Language :: Python :: 3.13
Requires-Dist: arrow (>=1.4.0,<2.0.0)
Requires-Dist: google-api-python-client (>=2.186.0,<3.0.0)
Requires-Dist: google-auth-oauthlib (>=1.2.3,<2.0.0)
Requires-Dist: jinja2 (>=3.1.6,<4.0.0)
Requires-Dist: levenshtein (>=0.27.3,<0.28.0)
Requires-Dist: pytimeparse (>=1.1.8,<2.0.0)
Requires-Dist: unidecode (>=1.4.0,<2.0.0)
